LICENSE
cryptocmd/__init__.py
cryptocmd/__version__.py
cryptocmd/core.py
cryptocmd/utils.py
cryptocmd-0.6.3.dist-info/LICENSE
cryptocmd-0.6.3.dist-info/METADATA
cryptocmd-0.6.3.dist-info/WHEEL
cryptocmd-0.6.3.dist-info/RECORD
