Metadata-Version: 2.1
Name: cryptocmd
Version: 0.6.3
Summary: Cryptocurrency historical market price data scrapper.
Home-page: https://github.com/guptarohit/cryptoCMD
License: BSD-3-Clause
Keywords: cryptocurrency,cryptocurrency historical data,coinmarketcap,dataset,historical cryptocurrency prices
Author: Rohit Gupta
Author-email: rohitgtech+git@gmail.com
Requires-Python: >=3.7,<4.0
Classifier: Development Status :: 4 - Beta
Classifier: License :: OSI Approved :: BSD License
Classifier: Programming Language :: Python
Classifier: Programming Language :: Python :: 3
Classifier: Programming Language :: Python :: 3.7
Classifier: Programming Language :: Python :: 3.8
Classifier: Programming Language :: Python :: 3.9
Classifier: Programming Language :: Python :: 3.10
Classifier: Programming Language :: Python :: 3.11
Classifier: Topic :: Utilities
Requires-Dist: requests
Requires-Dist: tablib
Project-URL: Repository, https://github.com/guptarohit/cryptoCMD
